erclient/__init__.py
erclient/client.py
erclient/dascsvloader.py
erclient/dasgpxconverter.py
erclient/er_errors.py
erclient/schemas.py
erclient/version.py
earthranger_client-1.8.0.dist-info/METADATA
earthranger_client-1.8.0.dist-info/WHEEL
earthranger_client-1.8.0.dist-info/licenses/LICENSE
earthranger_client-1.8.0.dist-info/RECORD
