Metadata-Version: 2.4
Name: earthranger-client
Version: 1.8.0
Summary: Client for EarthRanger API
Project-URL: Homepage, http://github.com/PADAS/er-client
Author-email: EarthRanger <opensource@earthranger.com>
License: Apache-2.0
License-File: LICENSE
Keywords: EarthRanger,api
Classifier: Development Status :: 5 - Production/Stable
Classifier: Intended Audience :: Developers
Classifier: License :: OSI Approved :: Apache Software License
Classifier: Programming Language :: Python :: 3.8
Classifier: Programming Language :: Python :: 3.9
Classifier: Programming Language :: Python :: 3.10
Classifier: Programming Language :: Python :: 3.11
Classifier: Programming Language :: Python :: 3.12
Requires-Python: >=3.8
Requires-Dist: dateparser>=1.1.1
Requires-Dist: gpxpy>=1.5.0
Requires-Dist: httpx>=0.23.3
Requires-Dist: importlib-metadata; python_version < '3.8'
Requires-Dist: pydantic>=1.10.17
Requires-Dist: pytz>=2021.1
Requires-Dist: requests>=2.28.0
Provides-Extra: test
Requires-Dist: anyio; extra == 'test'
Requires-Dist: pytest-asyncio; extra == 'test'
Requires-Dist: pytest-mock; extra == 'test'
Requires-Dist: pytest>=8; extra == 'test'
Requires-Dist: respx>=0.22; extra == 'test'
